ob_events/__init__.py
ob_events/trigger.py
ob_events-0.2.0.dist-info/METADATA
ob_events-0.2.0.dist-info/WHEEL
ob_events-0.2.0.dist-info/RECORD
