Metadata-Version: 2.4
Name: ob-events
Version: 0.2.0
Summary: A minimal Python client to publish events to the Outerbounds platform.
Project-URL: Documentation, https://docs.metaflow.org
Author: Outerbounds, Inc.
License-Expression: LicenseRef-Proprietary
Keywords: MLOps,data science,machine learning
Classifier: Operating System :: OS Independent
Classifier: Programming Language :: Python :: 3
Requires-Python: ~=3.7
Requires-Dist: requests
Provides-Extra: aws
Requires-Dist: boto3; extra == 'aws'
